aria2r/__init__.py
aria2r/cli.py
aria2r-0.9.1.dist-info/LICENSE
aria2r-0.9.1.dist-info/METADATA
aria2r-0.9.1.dist-info/WHEEL
aria2r-0.9.1.dist-info/entry_points.txt
aria2r-0.9.1.dist-info/top_level.txt
aria2r-0.9.1.dist-info/RECORD
