Metadata-Version: 2.1
Name: aria2r
Version: 0.9.1
Summary: A Command line utility to add new downloads to a running aria2c instance
Home-page: UNKNOWN
Author: Darrick Herwehe
Author-email: darrick@exitcodeone.com
License: UNKNOWN
Project-URL: Documentation, https://aria2r.readthedocs.io
Project-URL: Source, https://github.com/darricktheprogrammer/aria2r
Project-URL: Tracker, https://github.com/darricktheprogrammer/aria2r/issues
Platform: UNKNOWN
Classifier: Development Status :: 4 - Beta
Classifier: Environment :: Console
Classifier: Intended Audience :: End Users/Desktop
Classifier: License :: OSI Approved :: MIT License
Classifier: Programming Language :: Python
Classifier: Programming Language :: Python :: 3
Classifier: Programming Language :: Python :: 3 :: Only
Classifier: Programming Language :: Python :: 3.6
Classifier: Topic :: Utilities
Requires-Python: >=3.6
Requires-Dist: configargparse
Requires-Dist: requests
Requires-Dist: xdg
